cnuniversitymap/__init__.py
cnuniversitymap/setup.py
cnuniversitymap/src/__init__.py
cnuniversitymap/src/data.py
cnuniversitymap/src/university.py
cnuniversitymap-1.0.0.dist-info/LICENSE.txt
cnuniversitymap-1.0.0.dist-info/METADATA
cnuniversitymap-1.0.0.dist-info/WHEEL
cnuniversitymap-1.0.0.dist-info/entry_points.txt
cnuniversitymap-1.0.0.dist-info/top_level.txt
cnuniversitymap-1.0.0.dist-info/RECORD
